safeway_coupons/__init__.py
safeway_coupons/__version__.py
safeway_coupons/accounts.py
safeway_coupons/app.py
safeway_coupons/chrome_driver.py
safeway_coupons/client.py
safeway_coupons/config.py
safeway_coupons/email.py
safeway_coupons/errors.py
safeway_coupons/methods.py
safeway_coupons/models.py
safeway_coupons/py.typed
safeway_coupons/safeway.py
safeway_coupons/session.py
safeway_coupons/utils.py
safeway_coupons-0.3.0.dist-info/LICENSE
safeway_coupons-0.3.0.dist-info/METADATA
safeway_coupons-0.3.0.dist-info/WHEEL
safeway_coupons-0.3.0.dist-info/entry_points.txt
safeway_coupons-0.3.0.dist-info/RECORD
