Metadata-Version: 2.3
Name: safeway-coupons
Version: 0.3.0
Summary: Automatic coupon clipper for Safeway's online "Safeway for U" coupons
License: GPL-3.0-or-later
Author: Stephen Kent
Author-email: smkent@smkent.net
Requires-Python: >=3.9,<4.0
Classifier: Development Status :: 4 - Beta
Classifier: Operating System :: OS Independent
Classifier: Topic :: Software Development :: Libraries :: Python Modules
Classifier: Typing :: Typed
Requires-Dist: dataclasses-json
Requires-Dist: requests
Requires-Dist: selenium (>=4.10)
Requires-Dist: standard-distutils (>=3.11.9,<4.0.0)
Requires-Dist: undetected-chromedriver (>=3.5.0)
Requires-Dist: webdriver-manager (>=3.8.6)
